block_snippets/__init__.py
block_snippets/response.py
block_snippets/utils.py
block_snippets/views.py
block_snippets/locale/cs/LC_MESSAGES/django.po
block_snippets/templatetags/__init__.py
block_snippets/templatetags/snippets.py
example/__init__.py
example/manage.py
example/dj/__init__.py
example/dj/urls.py
example/dj/wsgi.py
example/dj/apps/__init__.py
example/dj/apps/app/__init__.py
example/dj/apps/app/models.py
example/dj/apps/app/views.py
example/dj/apps/app/tests/__init__.py
example/dj/apps/app/tests/snippets.py
example/dj/settings/__init__.py
example/dj/settings/base.py
example/dj/settings/settings.py
skip_django_block_snippets-2.1.0.dist-info/LICENSE
skip_django_block_snippets-2.1.0.dist-info/METADATA
skip_django_block_snippets-2.1.0.dist-info/WHEEL
skip_django_block_snippets-2.1.0.dist-info/top_level.txt
skip_django_block_snippets-2.1.0.dist-info/RECORD
