Metadata-Version: 2.1
Name: skip-django-block-snippets
Version: 2.1.0
Summary: Django block snippets.
Home-page: https://github.com/skip-pay/django-block-snippets
Author: Lubos Matl
Author-email: matllubos@gmail.com
License: BSD
Keywords: django,snippets
Classifier: Development Status :: 3 - Alpha
Classifier: Environment :: Web Environment
Classifier: Framework :: Django
Classifier: Intended Audience :: Developers
Classifier: Intended Audience :: End Users/Desktop
Classifier: License :: OSI Approved :: BSD License
Classifier: Natural Language :: Czech
Classifier: Operating System :: OS Independent
Classifier: Programming Language :: Python
Classifier: Topic :: Internet :: WWW/HTTP :: Dynamic Content
Classifier: Topic :: Internet :: WWW/HTTP :: Site Management
License-File: LICENSE
Requires-Dist: django >=4.2
